github_checks/__init__.py
github_checks/cli.py
github_checks/github_api.py
github_checks/models.py
github_checks/formatters/__init__.py
github_checks/formatters/check_jsonschema.py
github_checks/formatters/mypy.py
github_checks/formatters/raw.py
github_checks/formatters/ruff.py
github_checks/formatters/sarif.py
github_checks/formatters/utils.py
github_checks-0.0.7.dist-info/licenses/LICENSE
github_checks-0.0.7.dist-info/METADATA
github_checks-0.0.7.dist-info/WHEEL
github_checks-0.0.7.dist-info/top_level.txt
github_checks-0.0.7.dist-info/RECORD
